{"parent":"minecraft:item/generated","textures":{"layer0":"minecraft:item/apple"},"overrides":[{"predicate":{"custom_model_data":10031},"model":"cooking_expansion:item/ia_auto/bacon_cooked"},{"predicate":{"custom_model_data":10032},"model":"cooking_expansion:item/ia_auto/bacon_raw"},{"predicate":{"custom_model_data":10033},"model":"cooking_expansion:item/ia_auto/banana"},{"predicate":{"custom_model_data":10034},"model":"cooking_expansion:item/ia_auto/banana_shake"},{"predicate":{"custom_model_data":10035},"model":"cooking_expansion:item/ia_auto/basil"},{"predicate":{"custom_model_data":10036},"model":"cooking_expansion:item/ia_auto/baugette"},{"predicate":{"custom_model_data":10037},"model":"cooking_expansion:item/ia_auto/beer"},{"predicate":{"custom_model_data":10038},"model":"cooking_expansion:item/ia_auto/burger"},{"predicate":{"custom_model_data":10039},"model":"cooking_expansion:item/ia_auto/butter"},{"predicate":{"custom_model_data":10040},"model":"cooking_expansion:item/ia_auto/carrot_juice"},{"predicate":{"custom_model_data":10041},"model":"cooking_expansion:item/ia_auto/chocolate_bar"},{"predicate":{"custom_model_data":10042},"model":"cooking_expansion:item/ia_auto/chocolate_bar_wrapped"},{"predicate":{"custom_model_data":10043},"model":"cooking_expansion:item/ia_auto/chocolate_donut"},{"predicate":{"custom_model_data":10044},"model":"cooking_expansion:item/ia_auto/chocolate_ice_cream"},{"predicate":{"custom_model_data":10045},"model":"cooking_expansion:item/ia_auto/cooked_chicken_thigh"},{"predicate":{"custom_model_data":10046},"model":"cooking_expansion:item/ia_auto/cooked_sausage"},{"predicate":{"custom_model_data":10047},"model":"cooking_expansion:item/ia_auto/crossaint"},{"predicate":{"custom_model_data":10048},"model":"cooking_expansion:item/ia_auto/crossaint_batter"},{"predicate":{"custom_model_data":10049},"model":"cooking_expansion:item/ia_auto/flour"},{"predicate":{"custom_model_data":10050},"model":"cooking_expansion:item/ia_auto/french_fries"},{"predicate":{"custom_model_data":10051},"model":"cooking_expansion:item/ia_auto/fried_egg"},{"predicate":{"custom_model_data":10052},"model":"cooking_expansion:item/ia_auto/frog_leg_cooked"},{"predicate":{"custom_model_data":10053},"model":"cooking_expansion:item/ia_auto/gotdog"},{"predicate":{"custom_model_data":10054},"model":"cooking_expansion:item/ia_auto/green_frog_raw"},{"predicate":{"custom_model_data":10055},"model":"cooking_expansion:item/ia_auto/honey_waffle"},{"predicate":{"custom_model_data":10056},"model":"cooking_expansion:item/ia_auto/kebab"},{"predicate":{"custom_model_data":10057},"model":"cooking_expansion:item/ia_auto/lettuce"},{"predicate":{"custom_model_data":10058},"model":"cooking_expansion:item/ia_auto/muffin"},{"predicate":{"custom_model_data":10059},"model":"cooking_expansion:item/ia_auto/olive_oil"},{"predicate":{"custom_model_data":10060},"model":"cooking_expansion:item/ia_auto/orange"},{"predicate":{"custom_model_data":10061},"model":"cooking_expansion:item/ia_auto/orange_frog_raw"},{"predicate":{"custom_model_data":10062},"model":"cooking_expansion:item/ia_auto/orange_juice"},{"predicate":{"custom_model_data":10063},"model":"cooking_expansion:item/ia_auto/pancake"},{"predicate":{"custom_model_data":10064},"model":"cooking_expansion:item/ia_auto/pancake_batter"},{"predicate":{"custom_model_data":10065},"model":"cooking_expansion:item/ia_auto/pancake_with_choco"},{"predicate":{"custom_model_data":10066},"model":"cooking_expansion:item/ia_auto/pancake_with_honey"},{"predicate":{"custom_model_data":10067},"model":"cooking_expansion:item/ia_auto/pasta"},{"predicate":{"custom_model_data":10068},"model":"cooking_expansion:item/ia_auto/pepper"},{"predicate":{"custom_model_data":10069},"model":"cooking_expansion:item/ia_auto/pizza"},{"predicate":{"custom_model_data":10070},"model":"cooking_expansion:item/ia_auto/raw_chicken_tigh"},{"predicate":{"custom_model_data":10071},"model":"cooking_expansion:item/ia_auto/raw_pancake_batter"},{"predicate":{"custom_model_data":10072},"model":"cooking_expansion:item/ia_auto/raw_pasta"},{"predicate":{"custom_model_data":10073},"model":"cooking_expansion:item/ia_auto/raw_sausage"},{"predicate":{"custom_model_data":10074},"model":"cooking_expansion:item/ia_auto/salt"},{"predicate":{"custom_model_data":10075},"model":"cooking_expansion:item/ia_auto/soup"},{"predicate":{"custom_model_data":10076},"model":"cooking_expansion:item/ia_auto/soup_glow_berry"},{"predicate":{"custom_model_data":10077},"model":"cooking_expansion:item/ia_auto/soup_warped_fungus_stew"},{"predicate":{"custom_model_data":10078},"model":"cooking_expansion:item/ia_auto/stawberry"},{"predicate":{"custom_model_data":10079},"model":"cooking_expansion:item/ia_auto/strawberry_shake"},{"predicate":{"custom_model_data":10080},"model":"cooking_expansion:item/ia_auto/taco"},{"predicate":{"custom_model_data":10081},"model":"cooking_expansion:item/ia_auto/toast"},{"predicate":{"custom_model_data":10082},"model":"cooking_expansion:item/ia_auto/toast_honey"},{"predicate":{"custom_model_data":10083},"model":"cooking_expansion:item/ia_auto/tomato"},{"predicate":{"custom_model_data":10084},"model":"cooking_expansion:item/ia_auto/tomato_paste"},{"predicate":{"custom_model_data":10085},"model":"cooking_expansion:item/ia_auto/tomato_shake"},{"predicate":{"custom_model_data":10086},"model":"cooking_expansion:item/ia_auto/tomato_soup"},{"predicate":{"custom_model_data":10087},"model":"cooking_expansion:item/ia_auto/vinegar"},{"predicate":{"custom_model_data":10088},"model":"cooking_expansion:item/ia_auto/waffle"},{"predicate":{"custom_model_data":10089},"model":"cooking_expansion:item/ia_auto/waffle_batter"},{"predicate":{"custom_model_data":10090},"model":"cooking_expansion:item/ia_auto/white_frog_raw"},{"predicate":{"custom_model_data":10091},"model":"cooking_expansion:item/ia_auto/wine"},{"predicate":{"custom_model_data":10092},"model":"cooking_expansion:item/ia_auto/yogurt"},{"predicate":{"custom_model_data":10093},"model":"item/apple"}]}